[{"receiptId":"1720944110","rDate":"2014-10-06T00:00Z","migrosEan":"7617027659239","quantNorm":2,"price":1.98,"pricePerUnit":0.99,"custId":131852,"id":4818},{"receiptId":"1720944110","rDate":"2014-10-06T00:00Z","migrosEan":"7617027556798","quantNorm":1,"price":0.99,"pricePerUnit":0.99,"custId":131852,"id":4819},{"receiptId":"1720944110","rDate":"2014-10-06T00:00Z","migrosEan":"7610632993613","quantNorm":1,"price":0.59,"pricePerUnit":0.59,"custId":131852,"id":4820},{"receiptId":"1720944110","rDate":"2014-10-06T00:00Z","migrosEan":"7610200035202","quantNorm":1,"price":0.69,"pricePerUnit":0.69,"custId":131852,"id":4821},{"receiptId":"1720944110","rDate":"2014-10-06T00:00Z","migrosEan":"7613269012146","quantNorm":1,"price":1.09,"pricePerUnit":1.09,"custId":131852,"id":4822},{"receiptId":"1427488395","rDate":"2014-01-04T00:00Z","migrosEan":"7610200035202","quantNorm":2,"price":1.3,"pricePerUnit":0.65,"custId":131852,"id":14678},{"receiptId":"1427488395","rDate":"2014-01-04T00:00Z","migrosEan":"7617300722278","quantNorm":2,"price":1.98,"pricePerUnit":0.99,"custId":131852,"id":14679},{"receiptId":"1427488395","rDate":"2014-01-04T00:00Z","migrosEan":"7610029037166","quantNorm":1,"price":12.6,"pricePerUnit":12.6,"custId":131852,"id":14680},{"receiptId":"1428647059","rDate":"2014-01-05T00:00Z","migrosEan":"7616700018332","quantNorm":2,"price":1.58,"pricePerUnit":0.79,"custId":131852,"id":14681},{"receiptId":"1428647059","rDate":"2014-01-05T00:00Z","migrosEan":"7617027659239","quantNorm":1,"price":0.99,"pricePerUnit":0.99,"custId":131852,"id":14682},{"receiptId":"1444869342","rDate":"2014-01-24T00:00Z","migrosEan":"7610632994122","quantNorm":1,"price":1.49,"pricePerUnit":1.49,"custId":131852,"id":14683},{"receiptId":"1444869342","rDate":"2014-01-24T00:00Z","migrosEan":"7610200035202","quantNorm":1,"price":0.69,"pricePerUnit":0.69,"custId":131852,"id":14684},{"receiptId":"1444869342","rDate":"2014-01-24T00:00Z","migrosEan":"7612300010165","quantNorm":2,"price":3.38,"pricePerUnit":1.69,"custId":131852,"id":14685},{"receiptId":"1444869342","rDate":"2014-01-24T00:00Z","migrosEan":"7617027577144","quantNorm":1,"price":0.55,"pricePerUnit":0.55,"custId":131852,"id":14686},{"receiptId":"1444869342","rDate":"2014-01-24T00:00Z","migrosEan":"7613269287247","quantNorm":1,"price":0.55,"pricePerUnit":0.55,"custId":131852,"id":14687},{"receiptId":"1444869342","rDate":"2014-01-24T00:00Z","migrosEan":"7617027577182","quantNorm":1,"price":0.55,"pricePerUnit":0.55,"custId":131852,"id":14688},{"receiptId":"1444869342","rDate":"2014-01-24T00:00Z","migrosEan":"7610200379351","quantNorm":1,"price":0.55,"pricePerUnit":0.55,"custId":131852,"id":14689},{"receiptId":"1444869342","rDate":"2014-01-24T00:00Z","migrosEan":"7617027577274","quantNorm":1,"price":0.55,"pricePerUnit":0.55,"custId":131852,"id":14690},{"receiptId":"1444869342","rDate":"2014-01-24T00:00Z","migrosEan":"7613269012146","quantNorm":1,"price":0.99,"pricePerUnit":0.99,"custId":131852,"id":14691},{"receiptId":"1444869342","rDate":"2014-01-24T00:00Z","migrosEan":"8710496976940","quantNorm":1,"price":3.49,"pricePerUnit":3.49,"custId":131852,"id":14692},{"receiptId":"1444869342","rDate":"2014-01-24T00:00Z","migrosEan":"7610200307729","quantNorm":1,"price":2.99,"pricePerUnit":2.99,"custId":131852,"id":14693},{"receiptId":"1449533066","rDate":"2014-01-29T00:00Z","migrosEan":"7610200035202","quantNorm":1,"price":0.69,"pricePerUnit":0.69,"custId":131852,"id":14694},{"receiptId":"1449533066","rDate":"2014-01-29T00:00Z","migrosEan":"7617027577144","quantNorm":1,"price":0.55,"pricePerUnit":0.55,"custId":131852,"id":14695},{"receiptId":"1449533066","rDate":"2014-01-29T00:00Z","migrosEan":"7616600710855","quantNorm":1,"price":0.55,"pricePerUnit":0.55,"custId":131852,"id":14696},{"receiptId":"1449533066","rDate":"2014-01-29T00:00Z","migrosEan":"7610200379351","quantNorm":1,"price":0.55,"pricePerUnit":0.55,"custId":131852,"id":14697},{"receiptId":"1449533066","rDate":"2014-01-29T00:00Z","migrosEan":"7613269012146","quantNorm":1,"price":0.99,"pricePerUnit":0.99,"custId":131852,"id":14698},{"receiptId":"1453015690","rDate":"2014-02-02T00:00Z","migrosEan":"7610200035202","quantNorm":1,"price":0.69,"pricePerUnit":0.69,"custId":131852,"id":14699},{"receiptId":"1453015690","rDate":"2014-02-02T00:00Z","migrosEan":"7612300010165","quantNorm":2,"price":3.38,"pricePerUnit":1.69,"custId":131852,"id":14700},{"receiptId":"1453015690","rDate":"2014-02-02T00:00Z","migrosEan":"7617027577144","quantNorm":1,"price":0.59,"pricePerUnit":0.59,"custId":131852,"id":14701},{"receiptId":"1453015690","rDate":"2014-02-02T00:00Z","migrosEan":"7610200379351","quantNorm":1,"price":0.59,"pricePerUnit":0.59,"custId":131852,"id":14702},{"receiptId":"1453015690","rDate":"2014-02-02T00:00Z","migrosEan":"7617027577274","quantNorm":1,"price":0.59,"pricePerUnit":0.59,"custId":131852,"id":14703},{"receiptId":"1453015690","rDate":"2014-02-02T00:00Z","migrosEan":"8710496976940","quantNorm":1,"price":3.49,"pricePerUnit":3.49,"custId":131852,"id":14704},{"receiptId":"1459321611","rDate":"2014-02-09T00:00Z","migrosEan":"7610200307729","quantNorm":1,"price":2.99,"pricePerUnit":2.99,"custId":131852,"id":14705},{"receiptId":"1461364982","rDate":"2014-02-11T00:00Z","migrosEan":"7610200388346","quantNorm":1,"price":2.49,"pricePerUnit":2.49,"custId":131852,"id":14706},{"receiptId":"1461364982","rDate":"2014-02-11T00:00Z","migrosEan":"7610632986776","quantNorm":2,"price":1.98,"pricePerUnit":0.99,"custId":131852,"id":14707},{"receiptId":"1461364982","rDate":"2014-02-11T00:00Z","migrosEan":"7610200035202","quantNorm":1,"price":0.69,"pricePerUnit":0.69,"custId":131852,"id":14708},{"receiptId":"1461364982","rDate":"2014-02-11T00:00Z","migrosEan":"7617027577144","quantNorm":1,"price":0.59,"pricePerUnit":0.59,"custId":131852,"id":14709},{"receiptId":"1461364982","rDate":"2014-02-11T00:00Z","migrosEan":"7610200379351","quantNorm":2,"price":1.18,"pricePerUnit":0.59,"custId":131852,"id":14710},{"receiptId":"1461364982","rDate":"2014-02-11T00:00Z","migrosEan":"7617027577274","quantNorm":1,"price":0.59,"pricePerUnit":0.59,"custId":131852,"id":14711},{"receiptId":"1462356608","rDate":"2014-02-12T00:00Z","migrosEan":"7610632990971","quantNorm":1,"price":4.24,"pricePerUnit":4.24,"custId":131852,"id":14712},{"receiptId":"1466795531","rDate":"2014-02-18T00:00Z","migrosEan":"7617027659239","quantNorm":1,"price":0.99,"pricePerUnit":0.99,"custId":131852,"id":14713},{"receiptId":"1466795531","rDate":"2014-02-18T00:00Z","migrosEan":"7610632993224","quantNorm":1,"price":0.55,"pricePerUnit":0.55,"custId":131852,"id":14714},{"receiptId":"1466795531","rDate":"2014-02-18T00:00Z","migrosEan":"7610200035202","quantNorm":1,"price":0.69,"pricePerUnit":0.69,"custId":131852,"id":14715},{"receiptId":"1466795531","rDate":"2014-02-18T00:00Z","migrosEan":"7612300010165","quantNorm":2,"price":3.38,"pricePerUnit":1.69,"custId":131852,"id":14716},{"receiptId":"1466795531","rDate":"2014-02-18T00:00Z","migrosEan":"7616600710855","quantNorm":2,"price":1.18,"pricePerUnit":0.59,"custId":131852,"id":14717},{"receiptId":"1466795531","rDate":"2014-02-18T00:00Z","migrosEan":"7610200379351","quantNorm":1,"price":0.59,"pricePerUnit":0.59,"custId":131852,"id":14718},{"receiptId":"1466795531","rDate":"2014-02-18T00:00Z","migrosEan":"7617027577274","quantNorm":2,"price":1.18,"pricePerUnit":0.59,"custId":131852,"id":14719},{"receiptId":"1466795531","rDate":"2014-02-18T00:00Z","migrosEan":"7613269012146","quantNorm":1,"price":1.05,"pricePerUnit":1.05,"custId":131852,"id":14720},{"receiptId":"1466795531","rDate":"2014-02-18T00:00Z","migrosEan":"8710496976940","quantNorm":1,"price":3.49,"pricePerUnit":3.49,"custId":131852,"id":14721},{"receiptId":"1466795531","rDate":"2014-02-18T00:00Z","migrosEan":"7610029014266","quantNorm":1,"price":9.4,"pricePerUnit":9.4,"custId":131852,"id":14722},{"receiptId":"1472018045","rDate":"2014-02-23T00:00Z","migrosEan":"7610632993224","quantNorm":1,"price":0.8,"pricePerUnit":0.8,"custId":131852,"id":14723},{"receiptId":"1472018045","rDate":"2014-02-23T00:00Z","migrosEan":"7610632984741","quantNorm":1,"price":0.99,"pricePerUnit":0.99,"custId":131852,"id":14724},{"receiptId":"1472018045","rDate":"2014-02-23T00:00Z","migrosEan":"7610632986776","quantNorm":1,"price":0.99,"pricePerUnit":0.99,"custId":131852,"id":14725},{"receiptId":"1472018045","rDate":"2014-02-23T00:00Z","migrosEan":"7610200035202","quantNorm":1,"price":0.69,"pricePerUnit":0.69,"custId":131852,"id":14726},{"receiptId":"1472018045","rDate":"2014-02-23T00:00Z","migrosEan":"7617027577144","quantNorm":1,"price":0.59,"pricePerUnit":0.59,"custId":131852,"id":14727},{"receiptId":"1472018045","rDate":"2014-02-23T00:00Z","migrosEan":"7610200379351","quantNorm":1,"price":0.59,"pricePerUnit":0.59,"custId":131852,"id":14728},{"receiptId":"1472018045","rDate":"2014-02-23T00:00Z","migrosEan":"7610029014266","quantNorm":1,"price":9.4,"pricePerUnit":9.4,"custId":131852,"id":14729},{"receiptId":"1476495347","rDate":"2014-02-28T00:00Z","migrosEan":"7610200035202","quantNorm":1,"price":0.69,"pricePerUnit":0.69,"custId":131852,"id":14730},{"receiptId":"1476495347","rDate":"2014-02-28T00:00Z","migrosEan":"7612300010165","quantNorm":2,"price":3.38,"pricePerUnit":1.69,"custId":131852,"id":14731},{"receiptId":"1476495347","rDate":"2014-02-28T00:00Z","migrosEan":"7617027577144","quantNorm":1,"price":0.59,"pricePerUnit":0.59,"custId":131852,"id":14732},{"receiptId":"1476495347","rDate":"2014-02-28T00:00Z","migrosEan":"7610200379351","quantNorm":2,"price":1.18,"pricePerUnit":0.59,"custId":131852,"id":14733},{"receiptId":"1476495347","rDate":"2014-02-28T00:00Z","migrosEan":"7617027577274","quantNorm":1,"price":0.59,"pricePerUnit":0.59,"custId":131852,"id":14734},{"receiptId":"1476495347","rDate":"2014-02-28T00:00Z","migrosEan":"7610200232977","quantNorm":1,"price":3.99,"pricePerUnit":3.99,"custId":131852,"id":14735},{"receiptId":"1480757100","rDate":"2014-03-04T00:00Z","migrosEan":"7610200035202","quantNorm":1,"price":0.69,"pricePerUnit":0.69,"custId":131852,"id":14736},{"receiptId":"1480757100","rDate":"2014-03-04T00:00Z","migrosEan":"7617027577144","quantNorm":1,"price":0.59,"pricePerUnit":0.59,"custId":131852,"id":14737},{"receiptId":"1480757100","rDate":"2014-03-04T00:00Z","migrosEan":"7616600710855","quantNorm":1,"price":0.59,"pricePerUnit":0.59,"custId":131852,"id":14738},{"receiptId":"1480757100","rDate":"2014-03-04T00:00Z","migrosEan":"7610200379351","quantNorm":1,"price":0.59,"pricePerUnit":0.59,"custId":131852,"id":14739},{"receiptId":"1480757100","rDate":"2014-03-04T00:00Z","migrosEan":"8710496976940","quantNorm":1,"price":3.49,"pricePerUnit":3.49,"custId":131852,"id":14740},{"receiptId":"1480757100","rDate":"2014-03-04T00:00Z","migrosEan":"7610029014266","quantNorm":1,"price":11.2,"pricePerUnit":11.2,"custId":131852,"id":14741},{"receiptId":"1483402826","rDate":"2014-03-08T00:00Z","migrosEan":"7610632994122","quantNorm":1,"price":1.49,"pricePerUnit":1.49,"custId":131852,"id":14742},{"receiptId":"1483402826","rDate":"2014-03-08T00:00Z","migrosEan":"7610200035196","quantNorm":1,"price":1.15,"pricePerUnit":1.15,"custId":131852,"id":14743},{"receiptId":"1483402826","rDate":"2014-03-08T00:00Z","migrosEan":"7617027577144","quantNorm":1,"price":0.59,"pricePerUnit":0.59,"custId":131852,"id":14744},{"receiptId":"1483402826","rDate":"2014-03-08T00:00Z","migrosEan":"7613269287247","quantNorm":1,"price":0.59,"pricePerUnit":0.59,"custId":131852,"id":14745},{"receiptId":"1483402826","rDate":"2014-03-08T00:00Z","migrosEan":"7616600710855","quantNorm":1,"price":0.59,"pricePerUnit":0.59,"custId":131852,"id":14746},{"receiptId":"1483402826","rDate":"2014-03-08T00:00Z","migrosEan":"7617027577274","quantNorm":1,"price":0.59,"pricePerUnit":0.59,"custId":131852,"id":14747},{"receiptId":"1483402826","rDate":"2014-03-08T00:00Z","migrosEan":"8710496976940","quantNorm":1,"price":3.49,"pricePerUnit":3.49,"custId":131852,"id":14748},{"receiptId":"1483402826","rDate":"2014-03-08T00:00Z","migrosEan":"7610200040374","quantNorm":1,"price":3.49,"pricePerUnit":3.49,"custId":131852,"id":14749},{"receiptId":"1490828729","rDate":"2014-03-15T00:00Z","migrosEan":"7617027659239","quantNorm":2,"price":1.98,"pricePerUnit":0.99,"custId":131852,"id":14750},{"receiptId":"1490828729","rDate":"2014-03-15T00:00Z","migrosEan":"7610632986776","quantNorm":2,"price":1.98,"pricePerUnit":0.99,"custId":131852,"id":14751},{"receiptId":"1490828729","rDate":"2014-03-15T00:00Z","migrosEan":"7610200035202","quantNorm":1,"price":0.69,"pricePerUnit":0.69,"custId":131852,"id":14752},{"receiptId":"1490828729","rDate":"2014-03-15T00:00Z","migrosEan":"7617027577144","quantNorm":1,"price":0.59,"pricePerUnit":0.59,"custId":131852,"id":14753},{"receiptId":"1490828729","rDate":"2014-03-15T00:00Z","migrosEan":"7616600710855","quantNorm":1,"price":0.59,"pricePerUnit":0.59,"custId":131852,"id":14754},{"receiptId":"1490828729","rDate":"2014-03-15T00:00Z","migrosEan":"8710496976940","quantNorm":1,"price":3.49,"pricePerUnit":3.49,"custId":131852,"id":14755},{"receiptId":"1500482743","rDate":"2014-03-25T00:00Z","migrosEan":"7610200035202","quantNorm":1,"price":0.69,"pricePerUnit":0.69,"custId":131852,"id":14756},{"receiptId":"1500482743","rDate":"2014-03-25T00:00Z","migrosEan":"7610029014266","quantNorm":1,"price":9.4,"pricePerUnit":9.4,"custId":131852,"id":14757},{"receiptId":"1505363999","rDate":"2014-03-31T00:00Z","migrosEan":"7617027659239","quantNorm":2,"price":1.98,"pricePerUnit":0.99,"custId":131852,"id":14758},{"receiptId":"1505363999","rDate":"2014-03-31T00:00Z","migrosEan":"7610632986776","quantNorm":2,"price":1.98,"pricePerUnit":0.99,"custId":131852,"id":14759},{"receiptId":"1505363999","rDate":"2014-03-31T00:00Z","migrosEan":"7610200035202","quantNorm":1,"price":0.69,"pricePerUnit":0.69,"custId":131852,"id":14760},{"receiptId":"1505363999","rDate":"2014-03-31T00:00Z","migrosEan":"7612300010165","quantNorm":2,"price":3.38,"pricePerUnit":1.69,"custId":131852,"id":14761},{"receiptId":"1505363999","rDate":"2014-03-31T00:00Z","migrosEan":"8710496976940","quantNorm":1,"price":3.49,"pricePerUnit":3.49,"custId":131852,"id":14762},{"receiptId":"1505363999","rDate":"2014-03-31T00:00Z","migrosEan":"7613269194156","quantNorm":1,"price":1.59,"pricePerUnit":1.59,"custId":131852,"id":14763},{"receiptId":"1510637330","rDate":"2014-04-05T00:00Z","migrosEan":"7617027659239","quantNorm":2,"price":1.98,"pricePerUnit":0.99,"custId":131852,"id":14764},{"receiptId":"1513816488","rDate":"2014-04-08T00:00Z","migrosEan":"7617027659239","quantNorm":1,"price":0.99,"pricePerUnit":0.99,"custId":131852,"id":14765},{"receiptId":"1513816488","rDate":"2014-04-08T00:00Z","migrosEan":"7610632984741","quantNorm":1,"price":0.99,"pricePerUnit":0.99,"custId":131852,"id":14766},{"receiptId":"1513816488","rDate":"2014-04-08T00:00Z","migrosEan":"7610200035202","quantNorm":1,"price":0.69,"pricePerUnit":0.69,"custId":131852,"id":14767},{"receiptId":"1513816488","rDate":"2014-04-08T00:00Z","migrosEan":"7612300010165","quantNorm":1,"price":1.69,"pricePerUnit":1.69,"custId":131852,"id":14768},{"receiptId":"1513816501","rDate":"2014-04-08T00:00Z","migrosEan":"7613269012146","quantNorm":1,"price":1.05,"pricePerUnit":1.05,"custId":131852,"id":14769},{"receiptId":"1520717681","rDate":"2014-04-15T00:00Z","migrosEan":"7610200388346","quantNorm":1,"price":2.79,"pricePerUnit":2.79,"custId":131852,"id":14770},{"receiptId":"1520717681","rDate":"2014-04-15T00:00Z","migrosEan":"7617027659239","quantNorm":2,"price":1.98,"pricePerUnit":0.99,"custId":131852,"id":14771},{"receiptId":"1520717681","rDate":"2014-04-15T00:00Z","migrosEan":"7610200035202","quantNorm":1,"price":0.69,"pricePerUnit":0.69,"custId":131852,"id":14772},{"receiptId":"1520717681","rDate":"2014-04-15T00:00Z","migrosEan":"7613269012146","quantNorm":1,"price":1.05,"pricePerUnit":1.05,"custId":131852,"id":14773},{"receiptId":"1520717681","rDate":"2014-04-15T00:00Z","migrosEan":"8710496976940","quantNorm":1,"price":3.49,"pricePerUnit":3.49,"custId":131852,"id":14774},{"receiptId":"1520717681","rDate":"2014-04-15T00:00Z","migrosEan":"7610029014266","quantNorm":1,"price":11.2,"pricePerUnit":11.2,"custId":131852,"id":14775},{"receiptId":"1521560139","rDate":"2014-04-16T00:00Z","migrosEan":"7617027539036","quantNorm":1,"price":1.7,"pricePerUnit":1.7,"custId":131852,"id":14776},{"receiptId":"1521560139","rDate":"2014-04-16T00:00Z","migrosEan":"7612300010165","quantNorm":2,"price":3.38,"pricePerUnit":1.69,"custId":131852,"id":14777},{"receiptId":"1525505595","rDate":"2014-04-21T00:00Z","migrosEan":"7617027539036","quantNorm":1,"price":1.26,"pricePerUnit":1.26,"custId":131852,"id":14778},{"receiptId":"1525505595","rDate":"2014-04-21T00:00Z","migrosEan":"7617027659239","quantNorm":2,"price":1.98,"pricePerUnit":0.99,"custId":131852,"id":14779},{"receiptId":"1525505595","rDate":"2014-04-21T00:00Z","migrosEan":"7610200035202","quantNorm":1,"price":0.69,"pricePerUnit":0.69,"custId":131852,"id":14780},{"receiptId":"1525505595","rDate":"2014-04-21T00:00Z","migrosEan":"7617027577144","quantNorm":1,"price":0.59,"pricePerUnit":0.59,"custId":131852,"id":14781},{"receiptId":"1525505595","rDate":"2014-04-21T00:00Z","migrosEan":"7616600710855","quantNorm":1,"price":0.59,"pricePerUnit":0.59,"custId":131852,"id":14782},{"receiptId":"1525505595","rDate":"2014-04-21T00:00Z","migrosEan":"7610200379351","quantNorm":1,"price":0.59,"pricePerUnit":0.59,"custId":131852,"id":14783},{"receiptId":"1525505595","rDate":"2014-04-21T00:00Z","migrosEan":"7617027577274","quantNorm":1,"price":0.59,"pricePerUnit":0.59,"custId":131852,"id":14784},{"receiptId":"1525505595","rDate":"2014-04-21T00:00Z","migrosEan":"8710496976940","quantNorm":1,"price":3.49,"pricePerUnit":3.49,"custId":131852,"id":14785},{"receiptId":"1532373521","rDate":"2014-04-28T00:00Z","migrosEan":"7610632993224","quantNorm":1,"price":0.81,"pricePerUnit":0.81,"custId":131852,"id":14786},{"receiptId":"1532373521","rDate":"2014-04-28T00:00Z","migrosEan":"7610632986776","quantNorm":2,"price":1.98,"pricePerUnit":0.99,"custId":131852,"id":14787},{"receiptId":"1538195030","rDate":"2014-05-04T00:00Z","migrosEan":"7610200035202","quantNorm":1,"price":0.69,"pricePerUnit":0.69,"custId":131852,"id":14788},{"receiptId":"1538195030","rDate":"2014-05-04T00:00Z","migrosEan":"7612300010165","quantNorm":2,"price":3.58,"pricePerUnit":1.79,"custId":131852,"id":14789},{"receiptId":"1538195030","rDate":"2014-05-04T00:00Z","migrosEan":"7617027577144","quantNorm":1,"price":0.59,"pricePerUnit":0.59,"custId":131852,"id":14790},{"receiptId":"1538195030","rDate":"2014-05-04T00:00Z","migrosEan":"7616600710855","quantNorm":1,"price":0.59,"pricePerUnit":0.59,"custId":131852,"id":14791},{"receiptId":"1538195030","rDate":"2014-05-04T00:00Z","migrosEan":"7610200379351","quantNorm":1,"price":0.59,"pricePerUnit":0.59,"custId":131852,"id":14792},{"receiptId":"1538195030","rDate":"2014-05-04T00:00Z","migrosEan":"7617027577274","quantNorm":1,"price":0.59,"pricePerUnit":0.59,"custId":131852,"id":14793},{"receiptId":"1538195030","rDate":"2014-05-04T00:00Z","migrosEan":"7610029014266","quantNorm":1,"price":8.8,"pricePerUnit":8.8,"custId":131852,"id":14794},{"receiptId":"1540549568","rDate":"2014-05-06T00:00Z","migrosEan":"7617027659239","quantNorm":2,"price":1.98,"pricePerUnit":0.99,"custId":131852,"id":14795},{"receiptId":"1540549568","rDate":"2014-05-06T00:00Z","migrosEan":"7610632961407","quantNorm":1,"price":0.99,"pricePerUnit":0.99,"custId":131852,"id":14796},{"receiptId":"1540549568","rDate":"2014-05-06T00:00Z","migrosEan":"7617027551762","quantNorm":1,"price":1.45,"pricePerUnit":1.45,"custId":131852,"id":14797},{"receiptId":"1540549568","rDate":"2014-05-06T00:00Z","migrosEan":"7610200035202","quantNorm":1,"price":0.69,"pricePerUnit":0.69,"custId":131852,"id":14798},{"receiptId":"1540549568","rDate":"2014-05-06T00:00Z","migrosEan":"8710496976940","quantNorm":1,"price":3.49,"pricePerUnit":3.49,"custId":131852,"id":14799},{"receiptId":"1550006581","rDate":"2014-05-16T00:00Z","migrosEan":"7617027539036","quantNorm":1,"price":1.34,"pricePerUnit":1.34,"custId":131852,"id":14800},{"receiptId":"1550006581","rDate":"2014-05-16T00:00Z","migrosEan":"7610632994122","quantNorm":1,"price":0.99,"pricePerUnit":0.99,"custId":131852,"id":14801},{"receiptId":"1550006581","rDate":"2014-05-16T00:00Z","migrosEan":"7610200035202","quantNorm":3,"price":2.07,"pricePerUnit":0.69,"custId":131852,"id":14802},{"receiptId":"1550006581","rDate":"2014-05-16T00:00Z","migrosEan":"7612300010165","quantNorm":2,"price":3.58,"pricePerUnit":1.79,"custId":131852,"id":14803},{"receiptId":"1550006581","rDate":"2014-05-16T00:00Z","migrosEan":"7617027577144","quantNorm":1,"price":0.59,"pricePerUnit":0.59,"custId":131852,"id":14804},{"receiptId":"1550006581","rDate":"2014-05-16T00:00Z","migrosEan":"7610200379351","quantNorm":1,"price":0.59,"pricePerUnit":0.59,"custId":131852,"id":14805},{"receiptId":"1550006581","rDate":"2014-05-16T00:00Z","migrosEan":"7617027577274","quantNorm":1,"price":0.59,"pricePerUnit":0.59,"custId":131852,"id":14806},{"receiptId":"1550006581","rDate":"2014-05-16T00:00Z","migrosEan":"7610200232977","quantNorm":1,"price":3.99,"pricePerUnit":3.99,"custId":131852,"id":14807},{"receiptId":"1550006581","rDate":"2014-05-16T00:00Z","migrosEan":"7610200040374","quantNorm":1,"price":3.49,"pricePerUnit":3.49,"custId":131852,"id":14808},{"receiptId":"1554972479","rDate":"2014-05-21T00:00Z","migrosEan":"7610632993613","quantNorm":1,"price":0.99,"pricePerUnit":0.99,"custId":131852,"id":14809},{"receiptId":"1554972479","rDate":"2014-05-21T00:00Z","migrosEan":"7610145641308","quantNorm":1,"price":1.19,"pricePerUnit":1.19,"custId":131852,"id":14810},{"receiptId":"1561360901","rDate":"2014-05-27T00:00Z","migrosEan":"7617027659239","quantNorm":1,"price":0.99,"pricePerUnit":0.99,"custId":131852,"id":14811},{"receiptId":"1561360901","rDate":"2014-05-27T00:00Z","migrosEan":"7610632993613","quantNorm":1,"price":0.59,"pricePerUnit":0.59,"custId":131852,"id":14812},{"receiptId":"1561360901","rDate":"2014-05-27T00:00Z","migrosEan":"7617027551762","quantNorm":1,"price":1.5,"pricePerUnit":1.5,"custId":131852,"id":14813},{"receiptId":"1561360901","rDate":"2014-05-27T00:00Z","migrosEan":"7610632986776","quantNorm":1,"price":0.89,"pricePerUnit":0.89,"custId":131852,"id":14814},{"receiptId":"1561360901","rDate":"2014-05-27T00:00Z","migrosEan":"7610200035202","quantNorm":1,"price":0.69,"pricePerUnit":0.69,"custId":131852,"id":14815},{"receiptId":"1561360901","rDate":"2014-05-27T00:00Z","migrosEan":"7612300010165","quantNorm":2,"price":3.58,"pricePerUnit":1.79,"custId":131852,"id":14816},{"receiptId":"1561360901","rDate":"2014-05-27T00:00Z","migrosEan":"7617027577144","quantNorm":1,"price":0.59,"pricePerUnit":0.59,"custId":131852,"id":14817},{"receiptId":"1561360901","rDate":"2014-05-27T00:00Z","migrosEan":"7610200379351","quantNorm":1,"price":0.59,"pricePerUnit":0.59,"custId":131852,"id":14818},{"receiptId":"1561360901","rDate":"2014-05-27T00:00Z","migrosEan":"7617027577274","quantNorm":1,"price":0.59,"pricePerUnit":0.59,"custId":131852,"id":14819},{"receiptId":"1561360901","rDate":"2014-05-27T00:00Z","migrosEan":"8710496976940","quantNorm":1,"price":3.49,"pricePerUnit":3.49,"custId":131852,"id":14820},{"receiptId":"1561360901","rDate":"2014-05-27T00:00Z","migrosEan":"7610029014266","quantNorm":1,"price":8.8,"pricePerUnit":8.8,"custId":131852,"id":14821},{"receiptId":"1566354570","rDate":"2014-06-01T00:00Z","migrosEan":"7610632993613","quantNorm":1,"price":0.59,"pricePerUnit":0.59,"custId":131852,"id":14822},{"receiptId":"1566354570","rDate":"2014-06-01T00:00Z","migrosEan":"7617027551762","quantNorm":1,"price":1.03,"pricePerUnit":1.03,"custId":131852,"id":14823},{"receiptId":"1566354570","rDate":"2014-06-01T00:00Z","migrosEan":"7610200035202","quantNorm":1,"price":0.69,"pricePerUnit":0.69,"custId":131852,"id":14824},{"receiptId":"1566354570","rDate":"2014-06-01T00:00Z","migrosEan":"7612300010165","quantNorm":2,"price":3.58,"pricePerUnit":1.79,"custId":131852,"id":14825},{"receiptId":"1566354570","rDate":"2014-06-01T00:00Z","migrosEan":"7617027577144","quantNorm":1,"price":0.59,"pricePerUnit":0.59,"custId":131852,"id":14826},{"receiptId":"1566354570","rDate":"2014-06-01T00:00Z","migrosEan":"7616600710855","quantNorm":1,"price":0.59,"pricePerUnit":0.59,"custId":131852,"id":14827},{"receiptId":"1566354570","rDate":"2014-06-01T00:00Z","migrosEan":"7610200379351","quantNorm":1,"price":0.59,"pricePerUnit":0.59,"custId":131852,"id":14828},{"receiptId":"1566354570","rDate":"2014-06-01T00:00Z","migrosEan":"8710496976940","quantNorm":1,"price":3.49,"pricePerUnit":3.49,"custId":131852,"id":14829},{"receiptId":"1570288526","rDate":"2014-06-06T00:00Z","migrosEan":"7617027659239","quantNorm":2,"price":1.98,"pricePerUnit":0.99,"custId":131852,"id":14830},{"receiptId":"1570288512","rDate":"2014-06-06T00:00Z","migrosEan":"7617027556798","quantNorm":1,"price":1.54,"pricePerUnit":1.54,"custId":131852,"id":14831},{"receiptId":"1570288512","rDate":"2014-06-06T00:00Z","migrosEan":"7610632993613","quantNorm":1,"price":0.99,"pricePerUnit":0.99,"custId":131852,"id":14832},{"receiptId":"1570288512","rDate":"2014-06-06T00:00Z","migrosEan":"7610200035202","quantNorm":1,"price":0.69,"pricePerUnit":0.69,"custId":131852,"id":14833},{"receiptId":"1570288512","rDate":"2014-06-06T00:00Z","migrosEan":"7617027577144","quantNorm":1,"price":0.59,"pricePerUnit":0.59,"custId":131852,"id":14834},{"receiptId":"1570288512","rDate":"2014-06-06T00:00Z","migrosEan":"7617027577274","quantNorm":1,"price":0.59,"pricePerUnit":0.59,"custId":131852,"id":14835},{"receiptId":"1570288512","rDate":"2014-06-06T00:00Z","migrosEan":"7613269012146","quantNorm":1,"price":1.05,"pricePerUnit":1.05,"custId":131852,"id":14836},{"receiptId":"1570288512","rDate":"2014-06-06T00:00Z","migrosEan":"8710496976940","quantNorm":1,"price":3.49,"pricePerUnit":3.49,"custId":131852,"id":14837},{"receiptId":"1581323313","rDate":"2014-06-17T00:00Z","migrosEan":"7610632993224","quantNorm":1,"price":0.94,"pricePerUnit":0.94,"custId":131852,"id":14838},{"receiptId":"1581323313","rDate":"2014-06-17T00:00Z","migrosEan":"7610200035202","quantNorm":1,"price":0.69,"pricePerUnit":0.69,"custId":131852,"id":14839},{"receiptId":"1581323313","rDate":"2014-06-17T00:00Z","migrosEan":"7612300010165","quantNorm":2,"price":3.58,"pricePerUnit":1.79,"custId":131852,"id":14840},{"receiptId":"1581323313","rDate":"2014-06-17T00:00Z","migrosEan":"7616600710855","quantNorm":1,"price":0.59,"pricePerUnit":0.59,"custId":131852,"id":14841},{"receiptId":"1581323313","rDate":"2014-06-17T00:00Z","migrosEan":"7610200379351","quantNorm":1,"price":0.59,"pricePerUnit":0.59,"custId":131852,"id":14842},{"receiptId":"1587515662","rDate":"2014-06-22T00:00Z","migrosEan":"7617027659239","quantNorm":2,"price":1.98,"pricePerUnit":0.99,"custId":131852,"id":14843},{"receiptId":"1587515662","rDate":"2014-06-22T00:00Z","migrosEan":"7610632993613","quantNorm":1,"price":0.99,"pricePerUnit":0.99,"custId":131852,"id":14844},{"receiptId":"1587515662","rDate":"2014-06-22T00:00Z","migrosEan":"7617027551762","quantNorm":1,"price":1.41,"pricePerUnit":1.41,"custId":131852,"id":14845},{"receiptId":"1587515662","rDate":"2014-06-22T00:00Z","migrosEan":"7610632986776","quantNorm":1,"price":0.79,"pricePerUnit":0.79,"custId":131852,"id":14846},{"receiptId":"1587515662","rDate":"2014-06-22T00:00Z","migrosEan":"7610200035202","quantNorm":1,"price":0.69,"pricePerUnit":0.69,"custId":131852,"id":14847},{"receiptId":"1587515662","rDate":"2014-06-22T00:00Z","migrosEan":"7612300010165","quantNorm":1,"price":1.79,"pricePerUnit":1.79,"custId":131852,"id":14848},{"receiptId":"1587515662","rDate":"2014-06-22T00:00Z","migrosEan":"8710496976940","quantNorm":1,"price":3.49,"pricePerUnit":3.49,"custId":131852,"id":14849},{"receiptId":"1595649883","rDate":"2014-06-29T00:00Z","migrosEan":"7610632993613","quantNorm":1,"price":0.99,"pricePerUnit":0.99,"custId":131852,"id":14850},{"receiptId":"1595649883","rDate":"2014-06-29T00:00Z","migrosEan":"7610200035202","quantNorm":1,"price":0.69,"pricePerUnit":0.69,"custId":131852,"id":14851},{"receiptId":"1595649883","rDate":"2014-06-29T00:00Z","migrosEan":"7612300010165","quantNorm":2,"price":3.58,"pricePerUnit":1.79,"custId":131852,"id":14852},{"receiptId":"1595649883","rDate":"2014-06-29T00:00Z","migrosEan":"7616600710855","quantNorm":1,"price":0.59,"pricePerUnit":0.59,"custId":131852,"id":14853},{"receiptId":"1595649883","rDate":"2014-06-29T00:00Z","migrosEan":"7610200379351","quantNorm":1,"price":0.59,"pricePerUnit":0.59,"custId":131852,"id":14854},{"receiptId":"1595649883","rDate":"2014-06-29T00:00Z","migrosEan":"8710496976940","quantNorm":1,"price":3.49,"pricePerUnit":3.49,"custId":131852,"id":14855},{"receiptId":"1598822827","rDate":"2014-07-01T00:00Z","migrosEan":"7610632984741","quantNorm":1,"price":0.79,"pricePerUnit":0.79,"custId":131852,"id":14856},{"receiptId":"1598822827","rDate":"2014-07-01T00:00Z","migrosEan":"7610200035202","quantNorm":1,"price":0.69,"pricePerUnit":0.69,"custId":131852,"id":14857},{"receiptId":"1602162479","rDate":"2014-07-05T00:00Z","migrosEan":"8710496976940","quantNorm":1,"price":3.49,"pricePerUnit":3.49,"custId":131852,"id":14858},{"receiptId":"1607978391","rDate":"2014-07-08T00:00Z","migrosEan":"7617027953184","quantNorm":1,"price":1.2,"pricePerUnit":1.2,"custId":131852,"id":14859},{"receiptId":"1607978391","rDate":"2014-07-08T00:00Z","migrosEan":"7612300010165","quantNorm":2,"price":3.58,"pricePerUnit":1.79,"custId":131852,"id":14860},{"receiptId":"1607978391","rDate":"2014-07-08T00:00Z","migrosEan":"7610029014266","quantNorm":1,"price":8.8,"pricePerUnit":8.8,"custId":131852,"id":14861},{"receiptId":"1616920615","rDate":"2014-07-15T00:00Z","migrosEan":"7610200035202","quantNorm":1,"price":0.69,"pricePerUnit":0.69,"custId":131852,"id":14862},{"receiptId":"1616920615","rDate":"2014-07-15T00:00Z","migrosEan":"7612300010165","quantNorm":1,"price":1.79,"pricePerUnit":1.79,"custId":131852,"id":14863},{"receiptId":"1616920615","rDate":"2014-07-15T00:00Z","migrosEan":"7610200379351","quantNorm":1,"price":0.59,"pricePerUnit":0.59,"custId":131852,"id":14864},{"receiptId":"1616920615","rDate":"2014-07-15T00:00Z","migrosEan":"8710496976940","quantNorm":1,"price":3.49,"pricePerUnit":3.49,"custId":131852,"id":14865},{"receiptId":"1625363808","rDate":"2014-07-22T00:00Z","migrosEan":"7610200035202","quantNorm":2,"price":1.38,"pricePerUnit":0.69,"custId":131852,"id":14866},{"receiptId":"1625363808","rDate":"2014-07-22T00:00Z","migrosEan":"7612300010165","quantNorm":2,"price":3.58,"pricePerUnit":1.79,"custId":131852,"id":14867},{"receiptId":"1625363808","rDate":"2014-07-22T00:00Z","migrosEan":"7616600710855","quantNorm":1,"price":0.59,"pricePerUnit":0.59,"custId":131852,"id":14868},{"receiptId":"1625363808","rDate":"2014-07-22T00:00Z","migrosEan":"7610200379351","quantNorm":1,"price":0.59,"pricePerUnit":0.59,"custId":131852,"id":14869},{"receiptId":"1625363808","rDate":"2014-07-22T00:00Z","migrosEan":"8710496976940","quantNorm":1,"price":3.49,"pricePerUnit":3.49,"custId":131852,"id":14870},{"receiptId":"1634740228","rDate":"2014-07-30T00:00Z","migrosEan":"7612300010165","quantNorm":2,"price":3.58,"pricePerUnit":1.79,"custId":131852,"id":14871},{"receiptId":"1634740228","rDate":"2014-07-30T00:00Z","migrosEan":"7617027577144","quantNorm":1,"price":0.59,"pricePerUnit":0.59,"custId":131852,"id":14872},{"receiptId":"1634740228","rDate":"2014-07-30T00:00Z","migrosEan":"7616600710855","quantNorm":1,"price":0.59,"pricePerUnit":0.59,"custId":131852,"id":14873},{"receiptId":"1634740228","rDate":"2014-07-30T00:00Z","migrosEan":"7610200379351","quantNorm":1,"price":0.59,"pricePerUnit":0.59,"custId":131852,"id":14874},{"receiptId":"1634740228","rDate":"2014-07-30T00:00Z","migrosEan":"7617027577274","quantNorm":1,"price":0.59,"pricePerUnit":0.59,"custId":131852,"id":14875},{"receiptId":"1634740228","rDate":"2014-07-30T00:00Z","migrosEan":"8710496976940","quantNorm":1,"price":3.49,"pricePerUnit":3.49,"custId":131852,"id":14876},{"receiptId":"1634740228","rDate":"2014-07-30T00:00Z","migrosEan":"7610029037166","quantNorm":1,"price":12.8,"pricePerUnit":12.8,"custId":131852,"id":14877},{"receiptId":"1643440360","rDate":"2014-08-06T00:00Z","migrosEan":"7610632984741","quantNorm":1,"price":0.79,"pricePerUnit":0.79,"custId":131852,"id":14878},{"receiptId":"1643440360","rDate":"2014-08-06T00:00Z","migrosEan":"7610200035202","quantNorm":1,"price":0.69,"pricePerUnit":0.69,"custId":131852,"id":14879},{"receiptId":"1643440360","rDate":"2014-08-06T00:00Z","migrosEan":"7612300010165","quantNorm":2,"price":3.58,"pricePerUnit":1.79,"custId":131852,"id":14880},{"receiptId":"1643440360","rDate":"2014-08-06T00:00Z","migrosEan":"8710496976940","quantNorm":1,"price":3.49,"pricePerUnit":3.49,"custId":131852,"id":14881},{"receiptId":"1643440360","rDate":"2014-08-06T00:00Z","migrosEan":"7610029014266","quantNorm":1,"price":8.8,"pricePerUnit":8.8,"custId":131852,"id":14882},{"receiptId":"1648230240","rDate":"2014-08-10T00:00Z","migrosEan":"7610145641308","quantNorm":1,"price":1.29,"pricePerUnit":1.29,"custId":131852,"id":14883},{"receiptId":"1652027005","rDate":"2014-08-13T00:00Z","migrosEan":"7610632994122","quantNorm":1,"price":0.99,"pricePerUnit":0.99,"custId":131852,"id":14884},{"receiptId":"1652027005","rDate":"2014-08-13T00:00Z","migrosEan":"8710496976940","quantNorm":1,"price":3.49,"pricePerUnit":3.49,"custId":131852,"id":14885},{"receiptId":"1654666593","rDate":"2014-08-16T00:00Z","migrosEan":"7610632993613","quantNorm":1,"price":0.99,"pricePerUnit":0.99,"custId":131852,"id":14886},{"receiptId":"1654666593","rDate":"2014-08-16T00:00Z","migrosEan":"7610200035202","quantNorm":1,"price":0.69,"pricePerUnit":0.69,"custId":131852,"id":14887},{"receiptId":"1654666593","rDate":"2014-08-16T00:00Z","migrosEan":"7613269012146","quantNorm":1,"price":1.05,"pricePerUnit":1.05,"custId":131852,"id":14888},{"receiptId":"1665041757","rDate":"2014-08-24T00:00Z","migrosEan":"7616700223910","quantNorm":1,"price":1.09,"pricePerUnit":1.09,"custId":131852,"id":14889},{"receiptId":"1665041757","rDate":"2014-08-24T00:00Z","migrosEan":"7617027953184","quantNorm":1,"price":1.63,"pricePerUnit":1.63,"custId":131852,"id":14890},{"receiptId":"1665041757","rDate":"2014-08-24T00:00Z","migrosEan":"7610200035196","quantNorm":1,"price":1.15,"pricePerUnit":1.15,"custId":131852,"id":14891},{"receiptId":"1665041757","rDate":"2014-08-24T00:00Z","migrosEan":"7612300010165","quantNorm":1,"price":1.79,"pricePerUnit":1.79,"custId":131852,"id":14892},{"receiptId":"1665041757","rDate":"2014-08-24T00:00Z","migrosEan":"7617027577274","quantNorm":2,"price":1.18,"pricePerUnit":0.59,"custId":131852,"id":14893},{"receiptId":"1665041757","rDate":"2014-08-24T00:00Z","migrosEan":"8710496976940","quantNorm":1,"price":3.49,"pricePerUnit":3.49,"custId":131852,"id":14894},{"receiptId":"1677026448","rDate":"2014-09-02T00:00Z","migrosEan":"7610632993224","quantNorm":1,"price":0.55,"pricePerUnit":0.55,"custId":131852,"id":14895},{"receiptId":"1677026448","rDate":"2014-09-02T00:00Z","migrosEan":"7610632994122","quantNorm":1,"price":0.99,"pricePerUnit":0.99,"custId":131852,"id":14896},{"receiptId":"1677026448","rDate":"2014-09-02T00:00Z","migrosEan":"7610200035202","quantNorm":1,"price":0.69,"pricePerUnit":0.69,"custId":131852,"id":14897},{"receiptId":"1677026448","rDate":"2014-09-02T00:00Z","migrosEan":"7612300010165","quantNorm":2,"price":3.58,"pricePerUnit":1.79,"custId":131852,"id":14898},{"receiptId":"1677026448","rDate":"2014-09-02T00:00Z","migrosEan":"8710496976940","quantNorm":1,"price":3.49,"pricePerUnit":3.49,"custId":131852,"id":14899},{"receiptId":"1677026448","rDate":"2014-09-02T00:00Z","migrosEan":"7610029014266","quantNorm":1,"price":8.8,"pricePerUnit":8.8,"custId":131852,"id":14900},{"receiptId":"1687282785","rDate":"2014-09-10T00:00Z","migrosEan":"7617027953184","quantNorm":1,"price":2.02,"pricePerUnit":2.02,"custId":131852,"id":14901},{"receiptId":"1687282785","rDate":"2014-09-10T00:00Z","migrosEan":"7610632994122","quantNorm":1,"price":0.99,"pricePerUnit":0.99,"custId":131852,"id":14902},{"receiptId":"1687282785","rDate":"2014-09-10T00:00Z","migrosEan":"7610200035202","quantNorm":1,"price":0.69,"pricePerUnit":0.69,"custId":131852,"id":14903},{"receiptId":"1687282785","rDate":"2014-09-10T00:00Z","migrosEan":"7612300010165","quantNorm":2,"price":3.58,"pricePerUnit":1.79,"custId":131852,"id":14904},{"receiptId":"1687282785","rDate":"2014-09-10T00:00Z","migrosEan":"7610200040374","quantNorm":1,"price":3.49,"pricePerUnit":3.49,"custId":131852,"id":14905},{"receiptId":"1689455661","rDate":"2014-09-12T00:00Z","migrosEan":"7610200035202","quantNorm":1,"price":0.69,"pricePerUnit":0.69,"custId":131852,"id":14906},{"receiptId":"1689455661","rDate":"2014-09-12T00:00Z","migrosEan":"8710496976940","quantNorm":1,"price":3.49,"pricePerUnit":3.49,"custId":131852,"id":14907},{"receiptId":"1693781018","rDate":"2014-09-15T00:00Z","migrosEan":"7610632994122","quantNorm":1,"price":0.99,"pricePerUnit":0.99,"custId":131852,"id":14908},{"receiptId":"1693781018","rDate":"2014-09-15T00:00Z","migrosEan":"7610200035202","quantNorm":1,"price":0.69,"pricePerUnit":0.69,"custId":131852,"id":14909},{"receiptId":"1693781018","rDate":"2014-09-15T00:00Z","migrosEan":"7617027577144","quantNorm":1,"price":0.59,"pricePerUnit":0.59,"custId":131852,"id":14910},{"receiptId":"1693781018","rDate":"2014-09-15T00:00Z","migrosEan":"7617027577182","quantNorm":1,"price":0.59,"pricePerUnit":0.59,"custId":131852,"id":14911},{"receiptId":"1693781018","rDate":"2014-09-15T00:00Z","migrosEan":"8710496976940","quantNorm":1,"price":3.49,"pricePerUnit":3.49,"custId":131852,"id":14912},{"receiptId":"1696075686","rDate":"2014-09-17T00:00Z","migrosEan":"7610029014266","quantNorm":1,"price":8.8,"pricePerUnit":8.8,"custId":131852,"id":14913},{"receiptId":"1699794005","rDate":"2014-09-20T00:00Z","migrosEan":"7610632994122","quantNorm":1,"price":0.99,"pricePerUnit":0.99,"custId":131852,"id":14914},{"receiptId":"1699794005","rDate":"2014-09-20T00:00Z","migrosEan":"7612300010165","quantNorm":2,"price":3.78,"pricePerUnit":1.89,"custId":131852,"id":14915},{"receiptId":"1699794005","rDate":"2014-09-20T00:00Z","migrosEan":"7613269012146","quantNorm":1,"price":1.09,"pricePerUnit":1.09,"custId":131852,"id":14916},{"receiptId":"1699794005","rDate":"2014-09-20T00:00Z","migrosEan":"8710496976940","quantNorm":1,"price":3.49,"pricePerUnit":3.49,"custId":131852,"id":14917},{"receiptId":"1704877294","rDate":"2014-09-24T00:00Z","migrosEan":"7617027953184","quantNorm":1,"price":1.57,"pricePerUnit":1.57,"custId":131852,"id":14918},{"receiptId":"1704877294","rDate":"2014-09-24T00:00Z","migrosEan":"7610632994122","quantNorm":1,"price":0.99,"pricePerUnit":0.99,"custId":131852,"id":14919},{"receiptId":"1704877294","rDate":"2014-09-24T00:00Z","migrosEan":"7617027577182","quantNorm":2,"price":1.18,"pricePerUnit":0.59,"custId":131852,"id":14920},{"receiptId":"1704877294","rDate":"2014-09-24T00:00Z","migrosEan":"7617027577274","quantNorm":1,"price":0.59,"pricePerUnit":0.59,"custId":131852,"id":14921},{"receiptId":"1711647211","rDate":"2014-09-29T00:00Z","migrosEan":"7610632993613","quantNorm":1,"price":0.99,"pricePerUnit":0.99,"custId":131852,"id":14922},{"receiptId":"1711647211","rDate":"2014-09-29T00:00Z","migrosEan":"7610632986776","quantNorm":1,"price":0.79,"pricePerUnit":0.79,"custId":131852,"id":14923},{"receiptId":"1711647211","rDate":"2014-09-29T00:00Z","migrosEan":"7610200035202","quantNorm":1,"price":0.69,"pricePerUnit":0.69,"custId":131852,"id":14924},{"receiptId":"1711647211","rDate":"2014-09-29T00:00Z","migrosEan":"7612300010165","quantNorm":2,"price":3.78,"pricePerUnit":1.89,"custId":131852,"id":14925},{"receiptId":"1711647211","rDate":"2014-09-29T00:00Z","migrosEan":"7617027577182","quantNorm":1,"price":0.59,"pricePerUnit":0.59,"custId":131852,"id":14926},{"receiptId":"1711647211","rDate":"2014-09-29T00:00Z","migrosEan":"7617027577274","quantNorm":1,"price":0.59,"pricePerUnit":0.59,"custId":131852,"id":14927},{"receiptId":"1713224523","rDate":"2014-09-30T00:00Z","migrosEan":"7617027556798","quantNorm":1,"price":3.68,"pricePerUnit":3.68,"custId":131852,"id":14928},{"receiptId":"1713224523","rDate":"2014-09-30T00:00Z","migrosEan":"7610200035202","quantNorm":1,"price":0.69,"pricePerUnit":0.69,"custId":131852,"id":14929},{"receiptId":"1713224523","rDate":"2014-09-30T00:00Z","migrosEan":"8710496976940","quantNorm":1,"price":3.49,"pricePerUnit":3.49,"custId":131852,"id":14930},{"receiptId":"1713224523","rDate":"2014-09-30T00:00Z","migrosEan":"7610200010186","quantNorm":3,"price":3.57,"pricePerUnit":1.19,"custId":131852,"id":14931},{"receiptId":"1713224523","rDate":"2014-09-30T00:00Z","migrosEan":"7610029014266","quantNorm":1,"price":8.8,"pricePerUnit":8.8,"custId":131852,"id":14932}]