[{"receiptId":"1432468456","rDate":"2014-01-11T00:00Z","migrosEan":"7616700018332","quantNorm":2,"price":1.58,"pricePerUnit":0.79,"custId":199080,"id":61557},{"receiptId":"1434046344","rDate":"2014-01-12T00:00Z","migrosEan":"7616700018332","quantNorm":2,"price":1.58,"pricePerUnit":0.79,"custId":199080,"id":61558},{"receiptId":"1439558998","rDate":"2014-01-18T00:00Z","migrosEan":"7616700018332","quantNorm":2,"price":1.58,"pricePerUnit":0.79,"custId":199080,"id":61559},{"receiptId":"1441515194","rDate":"2014-01-20T00:00Z","migrosEan":"7616700018332","quantNorm":2,"price":1.58,"pricePerUnit":0.79,"custId":199080,"id":61560},{"receiptId":"1455205211","rDate":"2014-02-04T00:00Z","migrosEan":"7616700018332","quantNorm":2,"price":1.58,"pricePerUnit":0.79,"custId":199080,"id":61561},{"receiptId":"1479059593","rDate":"2014-03-03T00:00Z","migrosEan":"7616700018332","quantNorm":2,"price":1.58,"pricePerUnit":0.79,"custId":199080,"id":61562},{"receiptId":"1480756840","rDate":"2014-03-04T00:00Z","migrosEan":"7616700018332","quantNorm":2,"price":1.58,"pricePerUnit":0.79,"custId":199080,"id":61563},{"receiptId":"1483279684","rDate":"2014-03-07T00:00Z","migrosEan":"7616700018332","quantNorm":2,"price":1.58,"pricePerUnit":0.79,"custId":199080,"id":61564},{"receiptId":"1483279684","rDate":"2014-03-07T00:00Z","migrosEan":"7616700223910","quantNorm":1,"price":1.09,"pricePerUnit":1.09,"custId":199080,"id":61565},{"receiptId":"1483402268","rDate":"2014-03-08T00:00Z","migrosEan":"7616700018332","quantNorm":2,"price":1.58,"pricePerUnit":0.79,"custId":199080,"id":61566},{"receiptId":"1483403333","rDate":"2014-03-08T00:00Z","migrosEan":"7617027555975","quantNorm":1,"price":0.99,"pricePerUnit":0.99,"custId":199080,"id":61567},{"receiptId":"1483403333","rDate":"2014-03-08T00:00Z","migrosEan":"7617027551762","quantNorm":1,"price":1.77,"pricePerUnit":1.77,"custId":199080,"id":61568},{"receiptId":"1485241026","rDate":"2014-03-09T00:00Z","migrosEan":"7616700018332","quantNorm":2,"price":1.58,"pricePerUnit":0.79,"custId":199080,"id":61569},{"receiptId":"1486286668","rDate":"2014-03-10T00:00Z","migrosEan":"7616700018332","quantNorm":2,"price":1.58,"pricePerUnit":0.79,"custId":199080,"id":61570},{"receiptId":"1486770271","rDate":"2014-03-11T00:00Z","migrosEan":"7616700018332","quantNorm":2,"price":1.58,"pricePerUnit":0.79,"custId":199080,"id":61571},{"receiptId":"1489828867","rDate":"2014-03-14T00:00Z","migrosEan":"7616700018332","quantNorm":2,"price":1.58,"pricePerUnit":0.79,"custId":199080,"id":61572},{"receiptId":"1490828606","rDate":"2014-03-15T00:00Z","migrosEan":"7616700018332","quantNorm":2,"price":1.58,"pricePerUnit":0.79,"custId":199080,"id":61573},{"receiptId":"1491838323","rDate":"2014-03-16T00:00Z","migrosEan":"7616700018332","quantNorm":2,"price":1.58,"pricePerUnit":0.79,"custId":199080,"id":61574},{"receiptId":"1491838323","rDate":"2014-03-16T00:00Z","migrosEan":"7617027539036","quantNorm":1,"price":0.82,"pricePerUnit":0.82,"custId":199080,"id":61575},{"receiptId":"1492838201","rDate":"2014-03-17T00:00Z","migrosEan":"7616700018332","quantNorm":3,"price":2.37,"pricePerUnit":0.79,"custId":199080,"id":61576},{"receiptId":"1492838488","rDate":"2014-03-17T00:00Z","migrosEan":"7617027539036","quantNorm":1,"price":0.64,"pricePerUnit":0.64,"custId":199080,"id":61577},{"receiptId":"1498344025","rDate":"2014-03-23T00:00Z","migrosEan":"7616700018332","quantNorm":2,"price":1.58,"pricePerUnit":0.79,"custId":199080,"id":61578},{"receiptId":"1499371169","rDate":"2014-03-24T00:00Z","migrosEan":"7616700018332","quantNorm":2,"price":1.58,"pricePerUnit":0.79,"custId":199080,"id":61579},{"receiptId":"1500482442","rDate":"2014-03-25T00:00Z","migrosEan":"7616700018332","quantNorm":2,"price":1.58,"pricePerUnit":0.79,"custId":199080,"id":61580},{"receiptId":"1505363893","rDate":"2014-03-31T00:00Z","migrosEan":"7616700018332","quantNorm":2,"price":1.58,"pricePerUnit":0.79,"custId":199080,"id":61581},{"receiptId":"1506980494","rDate":"2014-04-01T00:00Z","migrosEan":"7616700018332","quantNorm":2,"price":1.58,"pricePerUnit":0.79,"custId":199080,"id":61582},{"receiptId":"1510637150","rDate":"2014-04-05T00:00Z","migrosEan":"7616700018332","quantNorm":3,"price":2.37,"pricePerUnit":0.79,"custId":199080,"id":61583},{"receiptId":"1512679994","rDate":"2014-04-07T00:00Z","migrosEan":"7616700018332","quantNorm":2,"price":1.58,"pricePerUnit":0.79,"custId":199080,"id":61584},{"receiptId":"1513816194","rDate":"2014-04-08T00:00Z","migrosEan":"7616700018332","quantNorm":2,"price":1.58,"pricePerUnit":0.79,"custId":199080,"id":61585},{"receiptId":"1513816643","rDate":"2014-04-08T00:00Z","migrosEan":"7617027539036","quantNorm":1,"price":0.68,"pricePerUnit":0.68,"custId":199080,"id":61586},{"receiptId":"1516327676","rDate":"2014-04-11T00:00Z","migrosEan":"7616700018332","quantNorm":2,"price":1.58,"pricePerUnit":0.79,"custId":199080,"id":61587},{"receiptId":"1518477755","rDate":"2014-04-13T00:00Z","migrosEan":"7616700018332","quantNorm":2,"price":1.58,"pricePerUnit":0.79,"custId":199080,"id":61588},{"receiptId":"1519483107","rDate":"2014-04-14T00:00Z","migrosEan":"7616700018332","quantNorm":2,"price":1.58,"pricePerUnit":0.79,"custId":199080,"id":61589},{"receiptId":"1521560001","rDate":"2014-04-16T00:00Z","migrosEan":"7616700018332","quantNorm":2,"price":1.58,"pricePerUnit":0.79,"custId":199080,"id":61590},{"receiptId":"1523185759","rDate":"2014-04-18T00:00Z","migrosEan":"7616700018332","quantNorm":3,"price":2.37,"pricePerUnit":0.79,"custId":199080,"id":61591},{"receiptId":"1525219830","rDate":"2014-04-20T00:00Z","migrosEan":"7616700018332","quantNorm":3,"price":2.37,"pricePerUnit":0.79,"custId":199080,"id":61592},{"receiptId":"1531324663","rDate":"2014-04-27T00:00Z","migrosEan":"7616700018332","quantNorm":2,"price":1.58,"pricePerUnit":0.79,"custId":199080,"id":61593},{"receiptId":"1537123516","rDate":"2014-05-03T00:00Z","migrosEan":"7617027539036","quantNorm":1,"price":0.77,"pricePerUnit":0.77,"custId":199080,"id":61594},{"receiptId":"1538194822","rDate":"2014-05-04T00:00Z","migrosEan":"7616700018332","quantNorm":3,"price":2.37,"pricePerUnit":0.79,"custId":199080,"id":61595},{"receiptId":"1543109749","rDate":"2014-05-09T00:00Z","migrosEan":"7617027539036","quantNorm":1,"price":1.23,"pricePerUnit":1.23,"custId":199080,"id":61596},{"receiptId":"1544134418","rDate":"2014-05-10T00:00Z","migrosEan":"7616700018332","quantNorm":2,"price":1.58,"pricePerUnit":0.79,"custId":199080,"id":61597},{"receiptId":"1550147701","rDate":"2014-05-17T00:00Z","migrosEan":"7616700018332","quantNorm":2,"price":1.58,"pricePerUnit":0.79,"custId":199080,"id":61598},{"receiptId":"1552105670","rDate":"2014-05-18T00:00Z","migrosEan":"7616700018332","quantNorm":2,"price":1.58,"pricePerUnit":0.79,"custId":199080,"id":61599},{"receiptId":"1554376880","rDate":"2014-05-20T00:00Z","migrosEan":"7616700018332","quantNorm":2,"price":1.58,"pricePerUnit":0.79,"custId":199080,"id":61600},{"receiptId":"1556923614","rDate":"2014-05-23T00:00Z","migrosEan":"7616700018332","quantNorm":2,"price":1.58,"pricePerUnit":0.79,"custId":199080,"id":61601},{"receiptId":"1556923614","rDate":"2014-05-23T00:00Z","migrosEan":"7617027539036","quantNorm":1,"price":0.75,"pricePerUnit":0.75,"custId":199080,"id":61602},{"receiptId":"1560070255","rDate":"2014-05-26T00:00Z","migrosEan":"7616700018332","quantNorm":3,"price":2.37,"pricePerUnit":0.79,"custId":199080,"id":61603},{"receiptId":"1572586649","rDate":"2014-06-08T00:00Z","migrosEan":"7616700018332","quantNorm":3,"price":2.37,"pricePerUnit":0.79,"custId":199080,"id":61604},{"receiptId":"1573678227","rDate":"2014-06-09T00:00Z","migrosEan":"7616700018332","quantNorm":2,"price":1.58,"pricePerUnit":0.79,"custId":199080,"id":61605},{"receiptId":"1587515387","rDate":"2014-06-22T00:00Z","migrosEan":"7616700018332","quantNorm":2,"price":1.58,"pricePerUnit":0.79,"custId":199080,"id":61606},{"receiptId":"1594100048","rDate":"2014-06-28T00:00Z","migrosEan":"7616700018332","quantNorm":2,"price":1.58,"pricePerUnit":0.79,"custId":199080,"id":61607},{"receiptId":"1602162147","rDate":"2014-07-05T00:00Z","migrosEan":"7616700018332","quantNorm":2,"price":1.58,"pricePerUnit":0.79,"custId":199080,"id":61608},{"receiptId":"1602162147","rDate":"2014-07-05T00:00Z","migrosEan":"7617027539036","quantNorm":1,"price":0.76,"pricePerUnit":0.76,"custId":199080,"id":61609},{"receiptId":"1606352240","rDate":"2014-07-07T00:00Z","migrosEan":"7617027539036","quantNorm":1,"price":0.78,"pricePerUnit":0.78,"custId":199080,"id":61610},{"receiptId":"1612546713","rDate":"2014-07-12T00:00Z","migrosEan":"7616700018332","quantNorm":2,"price":1.58,"pricePerUnit":0.79,"custId":199080,"id":61611},{"receiptId":"1612546713","rDate":"2014-07-12T00:00Z","migrosEan":"7617027539036","quantNorm":1,"price":0.98,"pricePerUnit":0.98,"custId":199080,"id":61612},{"receiptId":"1613994029","rDate":"2014-07-13T00:00Z","migrosEan":"7616700018332","quantNorm":2,"price":1.58,"pricePerUnit":0.79,"custId":199080,"id":61613},{"receiptId":"1616920359","rDate":"2014-07-15T00:00Z","migrosEan":"7616700018332","quantNorm":3,"price":2.37,"pricePerUnit":0.79,"custId":199080,"id":61614},{"receiptId":"1625363594","rDate":"2014-07-22T00:00Z","migrosEan":"7616700018332","quantNorm":2,"price":1.58,"pricePerUnit":0.79,"custId":199080,"id":61615},{"receiptId":"1628360353","rDate":"2014-07-25T00:00Z","migrosEan":"7616700018332","quantNorm":2,"price":1.58,"pricePerUnit":0.79,"custId":199080,"id":61616},{"receiptId":"1632380598","rDate":"2014-07-28T00:00Z","migrosEan":"7616700018332","quantNorm":2,"price":1.58,"pricePerUnit":0.79,"custId":199080,"id":61617},{"receiptId":"1632380598","rDate":"2014-07-28T00:00Z","migrosEan":"7617027953184","quantNorm":1,"price":1.13,"pricePerUnit":1.13,"custId":199080,"id":61618},{"receiptId":"1633863541","rDate":"2014-07-29T00:00Z","migrosEan":"7616700018332","quantNorm":2,"price":1.58,"pricePerUnit":0.79,"custId":199080,"id":61619},{"receiptId":"1636923496","rDate":"2014-08-01T00:00Z","migrosEan":"7617027539036","quantNorm":1,"price":0.95,"pricePerUnit":0.95,"custId":199080,"id":61620},{"receiptId":"1638270614","rDate":"2014-08-02T00:00Z","migrosEan":"7616700018332","quantNorm":3,"price":2.37,"pricePerUnit":0.79,"custId":199080,"id":61621},{"receiptId":"1639626095","rDate":"2014-08-03T00:00Z","migrosEan":"7616700018332","quantNorm":2,"price":1.58,"pricePerUnit":0.79,"custId":199080,"id":61622},{"receiptId":"1639626095","rDate":"2014-08-03T00:00Z","migrosEan":"7617027953184","quantNorm":1,"price":1.31,"pricePerUnit":1.31,"custId":199080,"id":61623},{"receiptId":"1641135161","rDate":"2014-08-05T00:00Z","migrosEan":"7616700018332","quantNorm":2,"price":1.58,"pricePerUnit":0.79,"custId":199080,"id":61624},{"receiptId":"1649590492","rDate":"2014-08-11T00:00Z","migrosEan":"7616700018332","quantNorm":3,"price":2.37,"pricePerUnit":0.79,"custId":199080,"id":61625},{"receiptId":"1663627037","rDate":"2014-08-23T00:00Z","migrosEan":"7616700018332","quantNorm":2,"price":1.58,"pricePerUnit":0.79,"custId":199080,"id":61626},{"receiptId":"1663627037","rDate":"2014-08-23T00:00Z","migrosEan":"7617027539036","quantNorm":1,"price":0.78,"pricePerUnit":0.78,"custId":199080,"id":61627},{"receiptId":"1666434020","rDate":"2014-08-25T00:00Z","migrosEan":"7616700018332","quantNorm":2,"price":1.58,"pricePerUnit":0.79,"custId":199080,"id":61628},{"receiptId":"1671010083","rDate":"2014-08-29T00:00Z","migrosEan":"7616700018332","quantNorm":3,"price":2.37,"pricePerUnit":0.79,"custId":199080,"id":61629},{"receiptId":"1693780932","rDate":"2014-09-15T00:00Z","migrosEan":"7616700018332","quantNorm":2,"price":1.58,"pricePerUnit":0.79,"custId":199080,"id":61630},{"receiptId":"1698401611","rDate":"2014-09-19T00:00Z","migrosEan":"7616700018332","quantNorm":2,"price":1.58,"pricePerUnit":0.79,"custId":199080,"id":61631}]